<PAMDataset>
  <SRS>PROJCS[&quot;NAD_1983_UTM_Zone_12N&quot;,GEOGCS[&quot;GCS_North_American_1983&quot;,DATUM[&quot;North_American_Datum_1983&quot;,SPHEROID[&quot;GRS_1980&quot;,6378137.0,298.257222101]],PRIMEM[&quot;Greenwich&quot;,0.0],UNIT[&quot;Degree&quot;,0.0174532925199433]],PROJECTION[&quot;Transverse_Mercator&quot;],PARAMETER[&quot;False_Easting&quot;,500000.0],PARAMETER[&quot;False_Northing&quot;,0.0],PARAMETER[&quot;Central_Meridian&quot;,-111.0],PARAMETER[&quot;Scale_Factor&quot;,0.9996],PARAMETER[&quot;Latitude_Of_Origin&quot;,0.0],UNIT[&quot;Meter&quot;,1.0]]</SRS>
  <Metadata>
    <MDI key="PyramidResamplingType">NEAREST</MDI>
  </Metadata>
  <PAMRasterBand band="1">
    <NoDataValue>2.56000000000000E+002</NoDataValue>
    <Histograms>
      <HistItem>
        <HistMin>-0.5</HistMin>
        <HistMax>255.5</HistMax>
        <BucketCount>256</BucketCount>
        <IncludeOutOfRange>1</IncludeOutOfRange>
        <Approximate>0</Approximate>
        <HistCounts>364239|0|0|0|0|0|0|0|0|0|0|0|0|0|0|0|0|0|0|0|0|0|0|0|0|0|0|0|0|0|0|0|0|0|0|0|0|0|0|0|0|0|9|0|0|0|0|0|0|0|0|0|0|0|0|0|0|0|0|0|0|0|0|0|0|0|0|0|0|0|0|0|0|0|0|0|0|0|0|0|0|0|0|0|0|0|9|0|0|18|0|0|0|0|0|0|0|0|0|0|9|0|0|0|0|0|0|0|0|0|0|0|9|0|0|0|0|9|0|9|0|0|0|0|0|0|0|0|0|0|0|0|0|0|0|0|0|0|0|0|1592984|188639|156646|144828|133484|184682|121332|114804|109263|165538|107097|108475|108379|107474|159331|108495|105925|108290|165492|110042|112481|112251|115196|175069|116797|123407|119489|126955|191541|128138|133252|130612|204042|137005|142565|146597|144143|223300|151611|151036|158744|240777|168275|170193|169439|177266|269570|191794|192744|195849|201017|310357|216789|219661|230055|348468|239304|249110|251369|260145|409093|284068|292730|299888|479374|335333|346122|358580|378321|588390|414795|431026|449879|471094|736722|503071|513528|507181|776103|531944|544231|608239|590450|837751|529559|507533|472195|675363|428614|408203|391023|381759|537804|339862|331560|316011|308635|442888|284263|271522|265930|398805|261159|258261|250989|248272|371647|243199|247210|238232|357496|221817|207480|182177|126319|57328</HistCounts>
      </HistItem>
    </Histograms>
    <Metadata>
      <MDI key="STATISTICS_MINIMUM">0</MDI>
      <MDI key="STATISTICS_MAXIMUM">255</MDI>
      <MDI key="STATISTICS_MEAN">203.35703511545</MDI>
      <MDI key="STATISTICS_STDDEV">37.197563976131</MDI>
    </Metadata>
  </PAMRasterBand>
</PAMDataset>
